etl-tools/__init__.py
etl-tools/etl.py
etl-tools/gcp.py
etl-tools/log.py
etl_tools/__init__.py
etl_tools/etl.py
etl_tools/gcp.py
etl_tools/log.py
etl_tools-0.2.data/data/etl_tools/log.conf
etl_tools-0.2.dist-info/LICENSE
etl_tools-0.2.dist-info/METADATA
etl_tools-0.2.dist-info/WHEEL
etl_tools-0.2.dist-info/top_level.txt
etl_tools-0.2.dist-info/RECORD
