Metadata-Version: 2.1
Name: etl-tools
Version: 0.2
Summary: ETL helper.
Home-page: UNKNOWN
Author: Szymon Lechwar
Author-email: sdfrew@kohls.com
License: MIT
Platform: UNKNOWN
